<?xml version='1.0' encoding='iso-8859-1'?>
<!DOCTYPE pregunta SYSTEM "./../../../clase.dtd">
<p>
  <q0>Read the first sentence and choose the correct alternative to complete the second sentence so that it means the
      same as the first.</q0>
  <g0></g0>
  <q>Sentence 1: Stop interrupting me all the time!</q>
  <g></g>
  <q2>Sentence 2: I wish you _____________ me.</q2>
  <g2></g2>
  <as r="R" correcta="1">
    <a>don't interrupt</a>
    <a>wouldn't interrupt</a>
    <a>shouldn't interrupt</a>
  </as>
  <x>B</x>
  <i></i>
  <x2></x2>
  <i2></i2>
  <v></v>
</p>