<?xml version='1.0' encoding='iso-8859-1'?>
<!DOCTYPE pregunta SYSTEM "./../../../clase.dtd">
<p>
	<q0></q0>
	<g0></g0>
	<q>¿Cuál es la manera correcta para agregar dependencias entre componentes de APX?</q>
   <g></g>
	<q2></q2>
   <g2></g2>
	<as r="R" correcta="2">
		<a>Agregar los tags dependency e import-packag en el pom del componente</a>
		<a>Ejecutando el comando mvn install dep</a>
		<a>Ejecutando el comando apx add dep</a>
		<a></a>
	</as>
	<x>C</x>
	<i></i>
	<x2>
	</x2>
	<i2></i2>
	<v1></v1>
</p>