<?xml version='1.0' encoding='iso-8859-1'?>
<!DOCTYPE pregunta SYSTEM "./../../../clase.dtd">
<p>
<q>Roberto, profesor de aula, frente a sus estudiantes, enfrenta una situación problemática, dotando de una estructura matemática, selecciona una alternativa de solución, interpreta, evalúa y valida su procedimiento y solución. Este hecho evidencia que tiene dominio de: 
</q>
<as r="R" correcta="2">
<a>Resolver ecuaciones. 
</a><a>Desarrollar buena sesión de clase. 
</a><a>Elaborar estrategias. 
</a><a>Tiene dominio de las matemáticas.</a>
</as>
<x>C.</x>
</p>